piscat/__init__.py
piscat/__main__.py
piscat/utils.py
piscat/Analysis/__init__.py
piscat/Analysis/analysis_protein_histogram.py
piscat/Analysis/analysis_protein_videos.py
piscat/Analysis/plot_protein_histogram.py
piscat/BackgroundCorrection/DRA.py
piscat/BackgroundCorrection/__init__.py
piscat/BackgroundCorrection/noise_floor.py
piscat/GUI/__init__.py
piscat/GUI/main.py
piscat/GUI/BackgroundCorrection/DRA.py
piscat/GUI/BackgroundCorrection/__init__.py
piscat/GUI/BackgroundCorrection/fun_bgCorrection.py
piscat/GUI/BatchAnalysis/__init__.py
piscat/GUI/BatchAnalysis/batch_data.py
piscat/GUI/BatchAnalysis/tab_analysis_protein.py
piscat/GUI/BatchAnalysis/tab_bg_correction.py
piscat/GUI/BatchAnalysis/tab_localization.py
piscat/GUI/BatchAnalysis/tab_plot_histogram.py
piscat/GUI/BatchAnalysis/tab_reading_data.py
piscat/GUI/BatchAnalysis/tab_trajectory.py
piscat/GUI/CPU_Configurations/Import_configuration.py
piscat/GUI/CPU_Configurations/__init__.py
piscat/GUI/CPU_Configurations/fun_CPU.py
piscat/GUI/InputOutput/__init__.py
piscat/GUI/InputOutput/fun_reading.py
piscat/GUI/InputOutput/help.py
piscat/GUI/InputOutput/import_RAW.py
piscat/GUI/InputOutput/import_im2vid.py
piscat/GUI/InputOutput/save_GUI.py
piscat/GUI/InputOutput/video_cropping.py
piscat/GUI/Memory/__init__.py
piscat/GUI/Memory/video_in_memory.py
piscat/GUI/Proccessing/__init__.py
piscat/GUI/Proccessing/spectrum.py
piscat/GUI/ProgressBar/__init__.py
piscat/GUI/ProgressBar/fun_progressBar.py
piscat/GUI/Projects/__init__.py
piscat/GUI/Projects/tab_bg_correction.py
piscat/GUI/Projects/tab_localization.py
piscat/GUI/Projects/tab_plot_histogram.py
piscat/GUI/Projects/tab_trajectory.py
piscat/GUI/Projects/Protein/GUI_Protein.py
piscat/GUI/Projects/Protein/Noise_floor.py
piscat/GUI/Projects/Protein/__init__.py
piscat/GUI/Projects/iPSF/__init__.py
piscat/GUI/Projects/iPSF/iPSF_model.py
piscat/GUI/VideoAnalysis/__init__.py
piscat/GUI/VideoAnalysis/video_analysis.py
piscat/GUI/VideoAnalysis/video_calculator.py
piscat-1.1.4.dist-info/METADATA
piscat-1.1.4.dist-info/WHEEL
piscat-1.1.4.dist-info/entry_points.txt
piscat-1.1.4.dist-info/licenses/LICENSE
piscat-1.1.4.dist-info/RECORD
