Metadata-Version: 2.3
Name: piscat
Version: 1.1.4
Summary: A high-performance library for interferometric scattering microscopy.
Project-URL: documentation, https://piscat.readthedocs.io/
Project-URL: source, https://github.com/SandoghdarLab/PiSCAT/
Project-URL: tracker, https://github.com/SandoghdarLab/PiSCAT/issues
Author: Houman Mirzaalian Dastjerdi, Marco Heisig, Matthias Baer, Reza Gholami, Mohammad Hossein Sheikhsaraf
Author-email: The PiSCAT Developers <piscat@mpl.mpg.de>
License-Expression: GPL-3.0-or-later
License-File: LICENSE
Keywords: Microscopy,iSCAT
Classifier: Intended Audience :: Science/Research
Classifier: Operating System :: OS Independent
Classifier: Programming Language :: Python :: 3
Classifier: Topic :: Scientific/Engineering :: Visualization
Requires-Python: >=3.8
Requires-Dist: astropy
Requires-Dist: flifile
Requires-Dist: gitpython
Requires-Dist: h5py
Requires-Dist: imageio-ffmpeg==0.4.5
Requires-Dist: ipywidgets
Requires-Dist: joblib
Requires-Dist: matplotlib
Requires-Dist: networkx
Requires-Dist: notebook
Requires-Dist: numba
Requires-Dist: numpy
Requires-Dist: opencv-python
Requires-Dist: pandas<2.0
Requires-Dist: psutil
Requires-Dist: pyqt6==6.2.3
Requires-Dist: pyqtgraph==0.12
Requires-Dist: pyqtwebengine
Requires-Dist: pyside6==6.2.3
Requires-Dist: pywavelets
Requires-Dist: requests
Requires-Dist: scikit-image
Requires-Dist: scikit-learn
Requires-Dist: scipy>=0.14.0
Requires-Dist: subprocess-run
Requires-Dist: tensorflow
Requires-Dist: tifffile
Requires-Dist: tqdm
Requires-Dist: trackpy
Requires-Dist: wget
Provides-Extra: dev
Requires-Dist: black; extra == 'dev'
Requires-Dist: isort; extra == 'dev'
Requires-Dist: pre-commit; extra == 'dev'
Requires-Dist: pycodestyle; extra == 'dev'
Requires-Dist: ruff; extra == 'dev'
Requires-Dist: typing-extensions; extra == 'dev'
Provides-Extra: test
Requires-Dist: coverage; extra == 'test'
Requires-Dist: pytest; extra == 'test'
Requires-Dist: pytest-benchmark[histogram]; extra == 'test'
Requires-Dist: pytest-cov; extra == 'test'
